{
  "date": "28-01-1936",
  "source": "Вечерняя Москва",
  "topic": "Молодняк в зоопарке",
  "summary": "В зоопарке зимой можно увидеть молодняка северных зверей, хотя к этому времени он вырастает и становится похож на взрослых особей. У трёх львиц зоопарка есть потомство, которое привлекает внимание посетителей.",
  "content": "НАТУРАЛИСТА АФРИКА\n  В ЗООПАРКЕ\n  Посетители Московекого зоопарка зимнее время, как правило, лишены возможности видеть молодняка наших северных зверей. К зиме этот молодняк настолько подрастает, что мало чем отличается от своих родителей. Но это не значит, что зимой в зоопарке нет молодняка.\n  Сейчас посещающие парк москвичи подолгу задерживаются перед клетками всех трёх львиц зоопарка, так как у всех трёх львиц есть детёныши, игры этих малышей с матерями представляют поистине очаровательное зрелище.\n  И вот естественно возникает вопрос: почему зимой есть молодняк у тропических животных и нет приплода у многочисленных представителей нашего северного царства зверей?\n  Дело в том, что у животных холодных стран — волков, лисиц, оленей, медведей, соболей, песцов — вся жизнь имеет ярко выраженную сезонность в соответствии с климатом. Детёныши рождаются у них только весной и в начале лета, так как рождённые в другое время года они должны были бы погибнуть от сурового климата, не успев окрепнуть.\n  Другое дело львы. Эти жители жаркой Африки у себя на родине могут с одинаковым успехом размножаться круглый год: там нет морозной зимы. Вот почему Московский воопарк\nпо- показывает в январе львят, но не может показать волчат.\n  K.",
  "entities": [
    "Московский зоопарк",
    "львицы",
    "львята",
    "детёныши",
    "волки",
    "лисицы",
    "олени",
    "медведи",
    "соболи",
    "песцы",
    "климат",
    "Африка",
    "приплод."
  ]
}