{
  "date": "08-01-1936",
  "source": "Вечерняя Москва",
  "topic": "Издевательство над зрителем",
  "summary": "Автор текста выражает недовольство по поводу ситуации, связанной с покупкой льготных студенческих билетов и обнаруженной им афишей в Мюзик-хол-.",
  "content": "- ИЗДЕВАТЕЛЬСТВО\nНАД ЗРИТЕЛЕМ\nЯ купил льготные студенческие\nбилеты в Мюзик-холл на 8 января.\nПрохожу на днях мимо Мюзик-хол-\nла и вижу афишу, в которой объявляется: «8 января открытый спектакль; деньги за билеты, купленные на это число, возвращаются обратно по месту покупки билета».\nНо в кассе Дома союзов, где я\nпокупал билеты, их у меня не приняли. Администрация Мюзик-холла\nне сообщила кассам\nоб отмене\nспектакля, и билеты на 8 января\nпродолжали продаваться.\nГРИГОРЬЕВ.",
  "entities": [
    "Мюзик-холл",
    "Дом союзов",
    "Григорьев."
  ]
}