{
  "date": "29-01-1936",
  "source": "Литературная газета",
  "topic": "О книге Кола\nБреньоне",
  "summary": "Литературный критик отмечает значимость книги «Кола\nБреньоне», указывая на её важность для понимания художественного направления.",
  "content": "3.\nПоистине можно сказать о «Кола\nБреньоне», что «эта книжка неболь-\nшая томов премногих тяжелей». Для\nнас, литературных критиков, она осо-\nбенно интересна тем, что дает ключ\nк художественному мироощущению\nРомэн Роллана. Она показывает, как\nогромна лотребность великого фран-\nцузского писателя в здоровом опти-\nмизме и как трудно было художнику\nконкретизировать этот оптимизм на\nпочве буржуазного общества.\nЗдоровый смех Кола Бреньона Ро-\nмэн Роллан часто вынужден был за-\nглушать в своем творчестве так же,\nкак он был вынужден задержать на\nпять лет опубликование этой весе-",
  "entities": [
    "Кола Бреньон",
    "Ромэн Роллан",
    "буржуазное общество."
  ]
}