{
  "date": "29-01-1936",
  "source": "Литературная газета",
  "topic": "Открытое письмо к Уолдо",
  "summary": "В открытом письме говорится о том, что судьба западного мира зависит от исхода борьбы между силами реакции и силами возрождения. Подчёркивается важность роли, которую в этот критический момент играет адресат письма, олицетворяющий для автора дух мира и гениальность французской культуры.",
  "content": "[\"ОТКРЫТОЕ ПИСЬМО\nРОМЗН РОЛЛАНУ\nУолдо ФРЭНК\nВаш\n\n70-летний юбилей пришелся в\nо время, когда непосредственно в\nБуках Францни находится судьба\nсего западного мира. Результат\nборьбы, которая идет во Франции\nежду силами реакции, силами смер-\nти, нашедшими сяае вырежние в\nбоевых крестах», и силами возрож-\nения, силами жизни, нашедшими\nвое выражение в едином народном\nБронте, определит результат\nэтой\nБорьбы во всем западном мире\nкрайней мере для нынешнего по-\nколения. Если Франция уступит ре-\nакции, уступит и Великобритания, а\nемные силы, обнажившие после це-\nтого века господства капиталистиче-\nской анархни, могут ввергнуть в бед-\nтствие Америку. Если Франция усту-\nпит в борьбе, тогла сдастся и чело-\nвек Запада, Тогда для всех нас -\nфранцузов, англичан, американцев -\nможет наступить эпоха беспросвет-\nного мрака, и лишь в далеком буду-\nщем потомство наше вознесет вверх\nсветоч, котогый теперь держит Со-\nветский союз. В этот, критический\nдля всего человечества момент, Фран-\nции, как нередко бывало и прежде,\nпринадлежит большая роль. И, празд-\nнуя ваше семидесятилетие, мы ви-\nдим в вас, Ромэн Роллан, символ на-\nшей веры в вашу великую страну.\nВы великий человек, Ромэн Рол-\nлан, великая личность. - вы сим-\nвол мира, чегез вас говорит дух ми-\nра. В этот час кризиса вы для мно-\nгих в моей стране олицетворяете ге-\nний, уже восемь веков оплодотворя-\nющий французокую культуру.\nЭтот гений - своего рода простой\n«здравый смысл»-увы, редко встре-\nчающийся при капитализме как у от-\nдельных личностей, так и у коллек-\nтивов. Он прост, как проста сама\nсущность, как просто все универсаль-\nное. В нем сочетаются беспощадная\nясность перед лицом истины, непо-\nколебимая омелость в следовании за\nней, хотя бы для этого пришлось по-\nжертвовать индивидуальным миром\nи покоем; творческое прозрение, по-\nзволяющее настолько овладеть исти-\nной, что она еще теснее согласуется\nс интунтивным пониманием сущности\nчеловека, его достоинства и его судь-\nбы.\nКогда я теперь оглядываюсь на тот\nмир, в котором я прожил больше со-\nрока лет, встречая людей различного\nума, темперамента, таланта.\nменя\nудивляет, как редко встречается этот\nздравый смысл, и я перестаю пора-\nжаться тому, что мир пришел к та-\nкому жестокому и мучительному кри-\nзису.\nЛюдей гениальных - в обычном\nсмысле этого слова - не мало, не\nредки и люди, обладающие физичес-\nкой смелостью и воображением. Но\nстрашно редко встречаешь человека,\nспособного познать истину и продол-\nжающего ей служить даже тогда, ког-\nда служение ей приносит ему страда-\nние; страшно редко встречаешь че-\nловека, который, обладая воображе-\nнием и зная, что он может по высо-\nкой цене продать свой талант экспло-\nататорам и проститукам, правящим\nмиром, все же приносит свой талант\nв дар своим униженным братьям;\nстрашно редко встречаешь смелого\nчеловека, не опьяненного своей сме-\nлостью и отдающего себе отчет в про-\nисходящем, потому что легче управ-\nлять армиями, чем собственным я.\nБыть-может, придет время, когда\nлюдей, обладающих таким редким\n«адравым смыслом», у нас будет мно-\nго. Но теперь еще не наступила эпо-\nха этой зрелости человечества, и та-\nкие люди - исторические личности.\nВы - один из них, Ромән Роллан. У\nвас нет разрыва между убеждением\nи действием, между признанием исти-\nны и каждым словом и поступком,\nкотогыми вы можете способствовать\nее осуществлению, между ответствен-\nностью за ваше достоннство, как пре-\nемника всето наследства\nчеловече-\nства, и ответственностью за вяше до-\nстоинство, как слуги людей. Десять\nлет назад я назвал вас, Ромән Рол-\nлан, «цельным четовеком», сегодня\nя не нахожу для вас более достой-\nного определения, ибо цельный чело-\nвек тот, кто обладает тем здравым\nсмыслом, о каком я злесь говорю.\nЯ желаю, чтобы Франция достойно\nвосславила 70-летие своего великого\nсына, преемника тех интеллектуаль-\nных и этических качеств, которые\nсоздали ее величие. И только своими\nдействиями может она восславить\nего. Франция знает, гле лежит исти-\nна; хватит ли у нее атравого смыс-\nла, чтобы ей служить? Она знает,\nчто в наши дни истина прежде все-\nго - в бесстрашном осуществлении\nколлективной экономнечокой свобо-\nды, которая одна может претворить в\nжизнь лозунги свободы, равенства\nи братства, вот уже сто лет красую-\nщиеся на всех общественных адани-\nях Франции. Для этого Франция дол-\nжна со всейt суровостью очиститься\nот жадности\nинертности класса\nкапиталистов, ибо это\nзародыши\nсмерти. Для Франции пришел час\nосуществить все то, к чему ее обя-\nзывает-\n-перед самой собой и пе-\nред всем\nмиром\nее великая\nтрадиция. В этом осушествлении она\nдостигнет зрелости. Мучителен и\nгероичен будет ее\nнуть,\nно если\nФранция теперь не оправдает воз-\nлагаемых на нее надежд, она погиб-\nнет. Она совершит то самоубийство\nдуха, которое всегда предшествует\nсамоубийству тела.\nСила и прозрение великих нагодов\nотражаются, как в зеркале, в жизни\nих великих людей. И сегодня, глядя\nc надеждой на вас, Ромэн Роллан,\nФранция глядит на самое себя, Да\nизучит она ясный и чистый путь\nразвития ваших идей от гуманитар-\nного идеализма вашей буржуазной\nюности, через испытание войны, нау-\nчившей вас вилеть\nфакты универ-\nсального значения, к мощному рево-\nлюционному реализму, созданному ва-\nми ныне. И тогда, изучая вас, Фран-\nция поймет, что ваш путь - символ\nее собственного неизбежного пути\nразвития, если только Франция хо-\nчет быть достойной самой себя. И\nэтой мольбой, обращенной к Фран-\nции, этим вызовом, брошенным ей,\nэтой верой в нее, - я хочу по-свое-\nму славить ваше 70-летие, Ромән Рол-\nлан.\"]\n\n[\"«Кола Бреньон»\nна экране\nКинофабрикой Мосфильм намечено\nсоздание художественного звукового\nфильма «Кола Бреньон» по одноимен-\nному роману Ромэн Роллана. Фильм\nбулет поставлен в 1987 г.\"]",
  "entities": [
    "Ромэн Роллан",
    "Уолдо Фрэнк",
    "Франция",
    "Великобритания",
    "Америка",
    "Советский Союз",
    "капиталистическая анархия",
    "здравый смысл",
    "«Кола Бреньон»",
    "Мосфильм."
  ]
}