{
  "date": "29-01-1936",
  "source": "Литературная газета",
  "topic": null,
  "summary": null,
  "content": "- «Свите ясный, свите тихий.\nВильный, не сповитый.\nЗа щожь тобе одурено,\nКадилами окурено\nБагряницами укрыто\nИ святым христом добито…\nНе добито… стрепенись\nДа над нами просвитись…\nПросвитися… Будем, брате,\nC багряниц онучи драти,\nИз кадил люльки курити,\nКропилами ж, друже брате,\nНову хату вымитати.\nТ. Шевченко».\n\n  После стихотворения Шевченко сле-\nдует такая запись В. Лазаревского:\n«Как-то однажды гуляли мы ут-\nром по Неве, Шевченко, я и брат\nМих. Матв. Зашли к озеру… позав-\nтракать. Тут он в саду написал мне\nэто стихотворение.\nПодлинник где-то у меня, да не\nнайду. Кстати, когда Шевченко си-\nдел в крепости перед отправлением\nв ссылку, то на полях какой-то кни-\nги, данной ему для чтения, он напи-\nсал много стихов, отрезал эти листы\nи вынес в сапоге, и при прощании\nпередал брату Михаилу Матвеевичу,\nкоторый дал их на сохранение мне.\nГде они сохраняются теперь,\nбог\nвесть. Может лежат где-нибудь меж\nбумаг. Хорошо спрятаны. Сам он…\nих не помнит. Потрясающее впечат-\nление произведут эти образы, ска-\nзанные крестьянским языком и све-\nденные в крестьянекую хату».\nРазбор архива Лазаревского про-\nдолжается.",
  "entities": [
    "В интернете есть много сайтов с информацией на эту тему. [Посмотрите",
    "что нашлось в поиске](https://ya.ru)"
  ]
}