{
  "date": "09-01-1936",
  "source": "Вечерняя Москва",
  "topic": "Школьные будни",
  "summary": "В тексте описывается начало учебного дня после рождественских каникул в школе, где царит душная атмосфера и сонливость. Ученики должны написать сочинение.",
  "content": "ЗИМНЯЯ\nСКАЗКА\nЕвг. МАР\nА ШКОЛЬНЫМИ окнами метель пересыпает дома старого города блестками снежного нафталина.\nПервый день после рождественских каникул. Мы сидим за партами. В классе душно. Сонная одурь входит, кажется, органическим элементом в школьную атмосферу.\nУченические тетрадки лежат перед нами замертво на своих синих спинах. Тема сочинения, которое ученики должны написать сейчас, нанесена на тетрадочный лист. Эта тема называется: «Как мы провели зимние каникулы».\nКакая это была нудная в те времена тема! Морщим лоб. Розовеем под колер тетрадочной промокашки, а слова по-прежнему стекают с пера с медлительностью ледника, оползающего с гор.\nО чём писать? О том, что даже в кино нашего брата, младшеклассников, в те времена не пускали? Всё рождество в кинематографах шли картины только для взрослых. О том, как тоскливо тянулись свободные зимние дни, или об единственном радостном: во время каникул можно было не ходить в серую, казённую, чужую школу?\nОдна из замечательных особенностей наших советских каникул заключается в том, что сама наша школа является их организатором. Наши советские школы, горячо любимые детьми, в дни каникул становятся местом притяжения школьников, превращаются в весёлый детский клуб.",
  "entities": [
    "Евг. Мар",
    "школа",
    "зимние каникулы",
    "советские каникулы",
    "детский клуб."
  ]
}