{
  "date": "07-01-1936",
  "source": "Вечерняя Москва",
  "topic": "Набор на курсы подготовки",
  "summary": "Московский ТЕХНИКУМ\nим. М. С. ПРИЕМ Токарева объявляет дополнительный набор на курсы подготовки в ТЕХНИКУМ продолжительностью 5 месяцев.",
  "content": "- Московский ТЕХНИКУМ\nим. М. С. ПРИЕМ Токарева объявляет дополнительный набор на курсы подготовки в ТЕХНИКУМ. Курсы рассчитаны на 5 месяцев. На курсы принимаются лица со знаниями в объёме 7 классов неполной средней школы. Общежитиями и стипендией слушатели курсов обеспечиваться не будут. Запросы о приёме и подробные справки по адресу: Моск ва, Большая Калужская ул., дом № 63. Трамвай 10, 24, 26, 47, 51. 186. Дирекция мтт. московский химико-технологический\nмясной\nпромышленности",
  "entities": [
    "Московский ТЕХНИКУМ им. М. С. Токарева",
    "М. С. Токарев",
    "курсы подготовки",
    "Большая Калужская ул.",
    "дом № 63",
    "московский химико-технологический техникум мясной промышленности."
  ]
}