{
  "date": "07-01-1936",
  "source": "Вечерняя Москва",
  "topic": "Объявление о наборе на курсы",
  "summary": "Московские городские педагогические курсы по подготовке учителей начальной школы при [ORG_20] отделе Народного Образования объявляют набор слушателей. На курсы принимаются лица, ранее работавшие в педагогической сфере, и лица, имеющие высшее образование.",
  "content": "- Московские городские педагогические курсы по подготовке учителей начальной школы при [ORG_20] отделе Народного Образования объявляют набор слушателей на курсы. Принимаются: 1. Лица, ранее бывшие на педагогической работе. 2. Лица, имеющие высшее и среднее образование, но не занимавшиеся педагогическим трудом. 3. Допускаются лица, имеющие образование в объёме 8 классов средней школы. Слушатели обеспечиваются стипендией от 100 до 150 рублей в месяц. Занятия вечерние. Приём заявлений и испытания производятся до 10 января 1936 года. С 1 сентября 1936 года обучающиеся на курсах будут направлены на работу в школы города [LOC_21]. Все справки [PER_22] но с 13 час. до 22 час. по адресу: Б. Ордынка, 22. Дирекция.",
  "entities": [
    "Отдел Народного Образования",
    "Московские городские педагогические курсы",
    "Б. Ордынка",
    "22."
  ]
}