{
  "date": "21-01-1936",
  "source": "Вечерняя Москва",
  "topic": "Неполный текст статьи",
  "summary": "В предоставленном тексте не удаётся выделить отдельные статьи.",
  "content": "В предоставленном тексте не удаётся выделить отдельные статьи из-за отсутствия явных признаков структурирования и большого количества ошибок распознавания. Для корректной обработки требуется более качественный исходный материал.",
  "entities": [
    "ошибки распознавания",
    "структурирование текста",
    "исходный материал"
  ]
}