{
  "date": "17-01-1936",
  "source": "Вечерняя Москва",
  "topic": "Ограничение экспорта и производственные задания",
  "summary": "Опубликовано постановление СНК СССР об ограничении экспорта в НЕКОТОРЫЕ страны. В письме сообщается об успешном выполнении производственного задания по переработке урожая свёклы 1935 года.",
  "content": "ОБ ОГРАНИЧЕНИИ ЭКСПОРТА В НЕКОТОРЫЕ СТРАНЫ — ПОСТАНОВЛЕНИЕ СНК Со-\nюза ССР ОПУБЛИКОВАНО СЕГОДНЯ.\n\nВ письме товарищу Сталину начальник Главсахара тов. Одинцов, директора и инженеры трестов заводов, сахарной также лучшие стахановцы промышленности сообщают об успешном выполнении производственного задания стране из урожая свёклы 1935 года 130 миллионов пудов сахара. До конца производственного сезона заводы дадут ещё 11–12 миллионов пудов.\n\nВЧЕРА из Баку в Москву прибыла делегация трудящихся Азербайджана во главе с секретарём Ці ВКП(б Азер- с секретариата Азербайджана т. Багировым и председателем Совнаркома т. Рахмановым.\n\nВ афинах подписана торговая конвенция между СССР и Грецией на 1936 год.\n\nЗА 14 ЯНВАРЯ добыто угля 94,0 проц. плана, выплавлено чугуна — 90,3, стали — 88,9, прокатано 94,0. За 15 января погружено 77 593 вагона (104,9 проц. плана).\n\nНА ЯПОНОКОЙ УГОЛЬНОЙ КОНЦЕССИИ В Дуэ ВСЛЕДСТВИЕ ПРЕСТУПНОГО ПРЕНЕБРЕЖЕНИЯ КОНЦЕССИОНЕРА ВОПРОСАМ ТЕХНИКИ БЕЗОПАСНОСТИ СНОВА ПРОИЗОШЛИ ОБВАЛЫ ЛАВ В ШАХТАХ. ЧЕЛОВЕЧЕСКИХ ЖЕРТВ иет.",
  "entities": [
    "Сталин",
    "Одинцов",
    "Главсахар",
    "Багиров",
    "Рахманов",
    "Совнарком",
    "СССР",
    "Япония",
    "Дуэ",
    "угольная концессия",
    "торговая конвенция",
    "Баку",
    "Москва",
    "Афины",
    "Азербайджан",
    "ЦИК ВКП(б)"
  ]
}