{
  "date": "23-01-1936",
  "source": "Вечерняя Москва",
  "topic": "Матч-репортаж из прессы",
  "summary": "В статье говорится о готовности главного акционера туристского отеля «Панханс» в Земмеринге (Авст-\nрия) Цимдин что-то предоставить, а также упоминается, что матч-речь между Әйве и Алехи- можно считать решённым вопросом.",
  "content": "- МАТЧ-Р ЕВ АН Ш\nАЛЕХИН -- ЗЙВЕ\nМатч-реванш между Әйве и Алехи- ным можно считать вопросом решённым, — пишет «Прагер Прессе».\n\nГлавный акционер большого туристского отеля «Панханс» в Земмеринге (Авст-\nрия) Цимдин заявил ° своей готовности предоставить необходимые для матча материальные средства. Как Эйве, так и Алехни уже приняли предложение.\n\nЧемпион мира Эйве b своём ответе пишет, что он радуется возможности дать «своему другу» Алехину реванш так скоро. Как выяснилось, в отпуске летом 1936 года Эйве отказано, потому матч-реванш сможет состояться не ранее будущей зимы Организация турнира будет возложена на мастера Вольфа. Часть партий будет играться в Вене.",
  "entities": [
    "Эйве",
    "Алехин",
    "«Прагер Прессе»",
    "Цимдин",
    "«Панханс»",
    "Земмеринг",
    "Австрия",
    "Вольф",
    "Вена."
  ]
}