{
  "date": "29-01-1936",
  "source": "Вечерняя Москва",
  "topic": null,
  "summary": null,
  "content": "- * группа членов обеих палат\nяпонского\nпарламента\nвносит\nпроект\nзакона\nпринудительной\nсте\nрилизации\n«неполноценных\nграждан».\nПроект закона\nразработан\nпо\nобразцу\nсоответствующего\nгерманского\nзакона\n°\nстерилизации.\n* ДЕЛЕГАТЫ БОЛИВИЙСКОГО ПРА\nвительства,\nсообщает\nкорреспондент\n«Пти Журналь» из Ла-Паса,\nотказались\nв последний момент подписатьм\nмирный\nдоговор,\nофициально\nпрекращающий\nвойну\nза нефтеносную область Гран\nЧако.\n* в пуэбла (Мексика) вспыхнула\nвсеобщая\nзабастовка.\nЖизнь в\nв городе\nзамерла.\nБастующие\nтребуют\nэкспро\nприации частных фабрик и земельных\nвладений.\n* АВСТРАЛИЙСКАЯ ЭКСПЕДИцИЯ,\nпроизводящая и\nизыскания на к\nюго-восто\nке страны,\nобнаружила\nнеизвестное до\nсих\nпор племя,\nнасчитывающее около\n200 тысяч человек. По внешности люди\nэтого\nплемени\nнапоминают\nдревних\nегиптян. Об уровне его р\nразвития г\nговорит сложная с\nсистема орошения. («Лю»).",
  "entities": [
    "Японский парламент",
    "закон принудительной стерилизации",
    "Германский закон стерилизации",
    "делегаты боливийского правительства",
    "Ла-Пас",
    "«Пти Журналь»",
    "Гран Чако",
    "всеобщая забастовка",
    "Пуэбла",
    "экспроприация",
    "Австралийская экспедиция",
    "племя"
  ]
}