{
  "date": "04-01-1936",
  "source": "Вечерняя Москва",
  "topic": "Культурный поход специалистов",
  "summary": "Встречи специалистов науки, искусств и техники с жителями новых колхозных деревень являются культурным почином огромной важности.",
  "content": "В помещении Московского обл\nнов текстильной секции союз\nМ. С. НАРОКОВ,\nзаслуженный деятель\nискусств\nКОЛХОЗНАЯ\nВСТРЕЧА\nТИ КОРОТКИЕ РЕЙДЫ крупных\nспециалистов науки, искусств и\nтехники в человеческую гущу но-\nвой колхозной деревни являются\nкультурным почином огромной важ-\nности. Пока это только первые\nвстречи, первые знакомства и, как\nвсякое первое знакомство, не сво-\nбодны еще от некоторого налета\nпарадности, от чуть-чуть стесни-\nтельного ритуала взаимных учтиво-\nстей. Но знакомство должно скоро\nстать прочной дружбой и вырасти\nв постоянную систему крепко орга-\nнизованных деловых связей, оди-\nнаково полезных для обеих сторон,\nценнейших связей для дела социа-\nлистической культуры в целом.\nНебесполезно было бы, конечно,\nуже и сейчас, освободившись от\nнекоторых лирических излишков,\nзаняться деловой проработкой про-\nделанного первого опыта нашего\nмассового культпохода, проводимого\nпо инициативе МК ВКП(б).",
  "entities": [
    "М. С. Нароков",
    "МК ВКП(б)",
    "колхозная деревня",
    "культпоход",
    "социалистическая культура."
  ]
}