{
  "date": "03-01-1936",
  "source": "Вечерняя Москва",
  "topic": "Театр Немировича-Данченко",
  "summary": "В тексте упоминается театр имени В. И. Немировича-Данченко.",
  "content": "T E A T R\nим. В. И. нЕМИро- 4/I утро сорочин\nвича-данченко, ская ярмарка.\nБ. Дмитровка,\n17.\nПРОДАЮТСЯ\n2 ТРАКТОРА\nшпалорезка.\nТелеф. 9-64-34 Фокин пер… 2.\n23544\nкомн, 13.",
  "entities": [
    "ТЕАТР им. В. И. Немировича-Данченко",
    "Б. Дмитровка",
    "Фокин пер.",
    "телефон 9-64-34",
    "трактор",
    "шпалорезка"
  ]
}