{
  "date": "26-01-1936",
  "source": "Вечерняя Москва",
  "topic": "Строительство в Горького развернутс",
  "summary": "В районе Горького развернутс ведётся строительство первого объекта, связанного с Союзе заво\nда по выработке перекиси водорода\nПо.",
  "content": "- B районе Горького развернутс строительство первого в Союзе заво\nда по выработке перекиси водорода\nПо своей производительности тонны 30-процентной перекиси водорода в сутки — этот завод будет крупнейшим в Европе.\nПуск завода намечается в июл 1936 года.",
  "entities": [
    "район Горького",
    "завод по выработке перекиси водорода",
    "перекись водорода",
    "Европа",
    "Союз"
  ]
}